dropbox_sign/__init__.py
dropbox_sign/api_client.py
dropbox_sign/api_response.py
dropbox_sign/configuration.py
dropbox_sign/event_callback_helper.py
dropbox_sign/exceptions.py
dropbox_sign/py.typed
dropbox_sign/rest.py
dropbox_sign/api/__init__.py
dropbox_sign/api/account_api.py
dropbox_sign/api/api_app_api.py
dropbox_sign/api/bulk_send_job_api.py
dropbox_sign/api/embedded_api.py
dropbox_sign/api/fax_api.py
dropbox_sign/api/fax_line_api.py
dropbox_sign/api/o_auth_api.py
dropbox_sign/api/report_api.py
dropbox_sign/api/signature_request_api.py
dropbox_sign/api/team_api.py
dropbox_sign/api/template_api.py
dropbox_sign/api/unclaimed_draft_api.py
dropbox_sign/apis/__init__.py
dropbox_sign/models/__init__.py
dropbox_sign/models/account_create_request.py
dropbox_sign/models/account_create_response.py
dropbox_sign/models/account_get_response.py
dropbox_sign/models/account_response.py
dropbox_sign/models/account_response_quotas.py
dropbox_sign/models/account_response_usage.py
dropbox_sign/models/account_update_request.py
dropbox_sign/models/account_verify_request.py
dropbox_sign/models/account_verify_response.py
dropbox_sign/models/account_verify_response_account.py
dropbox_sign/models/api_app_create_request.py
dropbox_sign/models/api_app_get_response.py
dropbox_sign/models/api_app_list_response.py
dropbox_sign/models/api_app_response.py
dropbox_sign/models/api_app_response_o_auth.py
dropbox_sign/models/api_app_response_options.py
dropbox_sign/models/api_app_response_owner_account.py
dropbox_sign/models/api_app_response_white_labeling_options.py
dropbox_sign/models/api_app_update_request.py
dropbox_sign/models/bulk_send_job_get_response.py
dropbox_sign/models/bulk_send_job_get_response_signature_requests.py
dropbox_sign/models/bulk_send_job_list_response.py
dropbox_sign/models/bulk_send_job_response.py
dropbox_sign/models/bulk_send_job_send_response.py
dropbox_sign/models/embedded_edit_url_request.py
dropbox_sign/models/embedded_edit_url_response.py
dropbox_sign-1.10.0.dist-info/licenses/LICENSE
dropbox_sign-1.10.0.dist-info/METADATA
dropbox_sign-1.10.0.dist-info/WHEEL
dropbox_sign-1.10.0.dist-info/top_level.txt
dropbox_sign-1.10.0.dist-info/RECORD
