Metadata-Version: 2.4
Name: dropbox-sign
Version: 1.10.0
Summary: Dropbox Sign API
Home-page: https://github.com/hellosign/dropbox-sign-python
Author: Dropbox Sign API Team
Author-email: apisupport@hellosign.com
License: MIT
Keywords: OpenAPI,OpenAPI-Generator,Dropbox Sign API
License-File: LICENSE
Requires-Dist: urllib3<3.0.0,>=1.25.3
Requires-Dist: python-dateutil>=2.8.2
Requires-Dist: pydantic>=2
Requires-Dist: typing-extensions>=4.7.1
Dynamic: author
Dynamic: author-email
Dynamic: description
Dynamic: description-content-type
Dynamic: home-page
Dynamic: keywords
Dynamic: license
Dynamic: license-file
Dynamic: requires-dist
Dynamic: summary
